cnftools/__init__.py
cnftools/io.py
cnftools/karps21.py
cnftools/simplify.py
cnftools/tseytin.py
cnftools/cli/__init__.py
cnftools/cli/cnf.py
cnftools/cli/simplify.py
cnftools/cli/stats.py
cnftools/cli/threecnf.py
cnftools/cli/karps21/__init__.py
cnftools/cli/karps21/chromaticnumber.py
cnftools/cli/karps21/cliquecover.py
cnftools/cli/karps21/graphs.py
tests/__init__.py
tests/fixtures.py
tests/test_karps21.py
tests/test_simplify.py
cnftools-0.0.2.dist-info/LICENSE
cnftools-0.0.2.dist-info/METADATA
cnftools-0.0.2.dist-info/WHEEL
cnftools-0.0.2.dist-info/entry_points.txt
cnftools-0.0.2.dist-info/top_level.txt
cnftools-0.0.2.dist-info/RECORD
